sim_calendar/calendar.py
sim_calendar/months.py
sim_calendar-0.1.1.dist-info/WHEEL
sim_calendar-0.1.1.dist-info/METADATA
sim_calendar-0.1.1.dist-info/RECORD
