Metadata-Version: 2.1
Name: sim-calendar
Version: 0.1.1
Summary: 
Author: Gabe Maayan
Author-email: gabemgem@gmail.com
Requires-Python: >=3.11,<4.0
Classifier: Programming Language :: Python :: 3
Classifier: Programming Language :: Python :: 3.11
Requires-Dist: datetime (>=4.7,<5.0)
